setup.py
TorCast/__init__.py
TorCast/client.py
TorCast.egg-info/PKG-INFO
TorCast.egg-info/SOURCES.txt
TorCast.egg-info/dependency_links.txt
TorCast.egg-info/requires.txt
TorCast.egg-info/top_level.txt