Metadata-Version: 1.0
Name: TorCast
Version: 0.0.0.3.pre
Summary: Broadcast messages to all tornado process subcribed on Redis asynchronously
Home-page: https://github.com/ipconfiger/TorCast
Author: Alexander.Li
Author-email: superpowerlee@gmail.com
License: LGPL
Keywords: tornado asynchronous redis message
Platform: UNKNOWN
